dowonpackage/__init__.py
dowonpackage/about.py
dowonpackage/constants.py
dowonpackage/corpus.py
dowonpackage/csvutils.py
dowonpackage/data.py
dowonpackage/downloader.py
dowonpackage/internals.py
dowonpackage/jvm.py
dowonpackage/utils.py
dowonpackage/data/corpus/kobill/1809890.txt
dowonpackage/data/corpus/kobill/1809891.txt
dowonpackage/data/corpus/kobill/1809892.txt
dowonpackage/data/corpus/kobill/1809893.txt
dowonpackage/data/corpus/kobill/1809894.txt
dowonpackage/data/corpus/kobill/1809895.txt
dowonpackage/data/corpus/kobill/1809896.txt
dowonpackage/data/corpus/kobill/1809897.txt
dowonpackage/data/corpus/kobill/1809898.txt
dowonpackage/data/corpus/kobill/1809899.txt
dowonpackage/data/corpus/kolaw/constitution.txt
dowonpackage/data/tagset/hannanum.json
dowonpackage/data/tagset/kkma.json
dowonpackage/data/tagset/komoran.json
dowonpackage/data/tagset/mecab.json
dowonpackage/data/tagset/twitter.json
dowonpackage/java/aho-corasick.jar
dowonpackage/java/jhannanum-0.8.4.jar
dowonpackage/java/kkma-2.0.jar
dowonpackage/java/komoran-3.0.jar
dowonpackage/java/open-korean-text-2.1.0.jar
dowonpackage/java/scala-library-2.12.3.jar
dowonpackage/java/shineware-common-1.0.jar
dowonpackage/java/shineware-ds-1.0.jar
dowonpackage/java/snakeyaml-1.12.jar
dowonpackage/java/twitter-text-1.14.7.jar
dowonpackage/java/bin/kr/lucypark/jhannanum/comm/HannanumInterface.class
dowonpackage/java/bin/kr/lucypark/jhannanum/hannanum/WorkflowFactory.class
dowonpackage/java/bin/kr/lucypark/kkma/KkmaInterface$1.class
dowonpackage/java/bin/kr/lucypark/kkma/KkmaInterface$2.class
dowonpackage/java/bin/kr/lucypark/kkma/KkmaInterface$3.class
dowonpackage/java/bin/kr/lucypark/kkma/KkmaInterface$4.class
dowonpackage/java/bin/kr/lucypark/kkma/KkmaInterface.class
dowonpackage/java/bin/kr/lucypark/okt/OktInterface.class
dowonpackage/java/conf/plugin/MajorPlugin/MorphAnalyzer/ChartMorphAnalyzer.json
dowonpackage/java/conf/plugin/MajorPlugin/PosTagger/HmmPosTagger.json
dowonpackage-0.0.9.dist-info/METADATA
dowonpackage-0.0.9.dist-info/WHEEL
dowonpackage-0.0.9.dist-info/top_level.txt
dowonpackage-0.0.9.dist-info/RECORD
